LICENSE
README.md
tracking51/__init__.py
tracking51/air_waybill.py
tracking51/const.py
tracking51/courier.py
tracking51/exception.py
tracking51/request.py
tracking51/response.py
tracking51/tracking.py
tracking51/util.py
51tracking-0.1.1.dist-info/LICENSE
51tracking-0.1.1.dist-info/METADATA
51tracking-0.1.1.dist-info/WHEEL
51tracking-0.1.1.dist-info/RECORD
