Metadata-Version: 2.1
Name: 51tracking
Version: 0.1.1
Summary: The Python SDK of 51Tracking API
Home-page: https://www.51tracking.com/v4/api-index/API-
Keywords: 51tracking,api,tracking
Author: 51Tracking
Author-email: service@51tracking.org
Requires-Python: >=3.7,<4.0
Classifier: Programming Language :: Python :: 3
Classifier: Programming Language :: Python :: 3.7
Classifier: Programming Language :: Python :: 3.8
Classifier: Programming Language :: Python :: 3.9
Classifier: Programming Language :: Python :: 3.10
Classifier: Programming Language :: Python :: 3.11
Requires-Dist: requests (>=2.31.0,<3.0.0)
Requires-Dist: urllib3 (==1.26.7)
Project-URL: Documentation, https://github.com/51tracking/51tracking-sdk-python
Project-URL: Repository, https://github.com/51tracking/51tracking-sdk-python
